{
  "productionMode": true,
  "production": {
    "token": "",
    "logLevel": 3,
    "prefixes": {
      "normal": ".",
      "custom": "!"
    },
    "vistorReactRole": {
      "memberRoleId": "",
      "visitorRoleId": "",
      "visitorEmojiId": "",
      "rolesChannelId": ""
    },
    "customCommandListChannelId": "",
    "imgurClientId": ""
  },
  "nonProduction": {
    "token": "",
    "logLevel": 3,
    "prefixes": {
      "normal": ".",
      "custom": "!"
    },
    "vistorReactRole": {
      "memberRoleId": "",
      "visitorRoleId": "",
      "visitorEmojiId": "",
      "rolesChannelId": ""
    },
    "customCommandListChannelId": "",
    "imgurClientId": "",
    "guildId": ""
  }
}
